pytodos/__init__.py
pytodos/colourful.py
pytodos/constants.py
pytodos/file_handler.py
pytodos/todo.py
pytodos-1.0.18.dist-info/DESCRIPTION.rst
pytodos-1.0.18.dist-info/METADATA
pytodos-1.0.18.dist-info/RECORD
pytodos-1.0.18.dist-info/WHEEL
pytodos-1.0.18.dist-info/entry_points.txt
pytodos-1.0.18.dist-info/metadata.json
pytodos-1.0.18.dist-info/top_level.txt
