Metadata-Version: 2.0
Name: pytodos
Version: 1.0.18
Summary: a command line lightweight todos tool.
Home-page: https://github.com/chuanwu/PyToDos.py
Author: chuanwu
Author-email: chuanwusun@gmail.com
License: UNKNOWN
Platform: UNKNOWN
Requires-Dist: click (==6.7)
Requires-Dist: enum (==0.4.6)
